StateModelRnD/__init__.py
StateModelRnD/to_numpy.py
StateModelRnD-0.4.2.dist-info/METADATA
StateModelRnD-0.4.2.dist-info/RECORD
StateModelRnD-0.4.2.dist-info/WHEEL
StateModelRnD-0.4.2.dist-info/top_level.txt
